sry_gnm_sy1xx_bl/__init__.py
sry_gnm_sy1xx_bl/generate_ganymed_image.py
sry_gnm_sy1xx_bl/logging_module.py
sry_gnm_sy1xx_bl/sry_gnm_sy1xx_bl.py
sry_gnm_sy1xx_bl/sy1xx_bootloader.py
sry_gnm_sy1xx_bl/threaded_serial_port_handler.py
sry_gnm_sy1xx_bl-0.1.8.dist-info/LICENSE
sry_gnm_sy1xx_bl-0.1.8.dist-info/METADATA
sry_gnm_sy1xx_bl-0.1.8.dist-info/WHEEL
sry_gnm_sy1xx_bl-0.1.8.dist-info/top_level.txt
sry_gnm_sy1xx_bl-0.1.8.dist-info/RECORD
