Metadata-Version: 2.2
Name: sry_gnm_sy1xx_bl
Version: 0.1.8
Summary: Sensry Ganymed Sy1xx Bootloader Tool
Author-email: Sven Ginka <s.ginka@sensry.de>
License: Apache License
Project-URL: Homepage, https://github.com/sensry-de/ganymed_sy1xx_bootloader_pypi
License-File: LICENSE
Requires-Dist: pyserial
